USEFS_ICS/__init__.py
USEFS_ICS-0.1.1.dist-info/LICENSE
USEFS_ICS-0.1.1.dist-info/METADATA
USEFS_ICS-0.1.1.dist-info/WHEEL
USEFS_ICS-0.1.1.dist-info/entry_points.txt
USEFS_ICS-0.1.1.dist-info/top_level.txt
USEFS_ICS-0.1.1.dist-info/RECORD
