Metadata-Version: 2.2
Name: USEFS_ICS
Version: 0.1.1
Summary: A tool for converting between USEFS and iCalendar files.
Author-email: SRInternet <srinternet@qq.com>
License: MIT License
Project-URL: homepage, https://github.com/SRInternet/USEFS_ICS
Project-URL: repository, https://github.com/SRInternet/USEFS_ICS
Classifier: Programming Language :: Python :: 3
Classifier: License :: OSI Approved :: MIT License
Classifier: Operating System :: OS Independent
Requires-Python: >=3.7
License-File: LICENSE
Requires-Dist: USEFS_Python>=0.2.0
Requires-Dist: icalendar
Requires-Dist: pytz
Provides-Extra: dev
Requires-Dist: pytest; extra == "dev"
